{
  "category_pools": {
    "metabolic": {
      "n_drugs": 199,
      "n_diseases": 74,
      "mean_breadth": 7.9296482412060305,
      "median_breadth": 4.0
    },
    "cardiovascular": {
      "n_drugs": 268,
      "n_diseases": 118,
      "mean_breadth": 6.2388059701492535,
      "median_breadth": 5.0
    },
    "autoimmune": {
      "n_drugs": 143,
      "n_diseases": 66,
      "mean_breadth": 12.27972027972028,
      "median_breadth": 5.0
    },
    "neurological": {
      "n_drugs": 121,
      "n_diseases": 110,
      "mean_breadth": 6.619834710743802,
      "median_breadth": 3.0
    },
    "infectious": {
      "n_drugs": 310,
      "n_diseases": 442,
      "mean_breadth": 9.270967741935484,
      "median_breadth": 3.0
    },
    "cancer": {
      "n_drugs": 417,
      "n_diseases": 658,
      "mean_breadth": 6.858513189448441,
      "median_breadth": 3.0
    },
    "respiratory": {
      "n_drugs": 140,
      "n_diseases": 74,
      "mean_breadth": 12.42142857142857,
      "median_breadth": 5.0
    },
    "psychiatric": {
      "n_drugs": 86,
      "n_diseases": 57,
      "mean_breadth": 5.976744186046512,
      "median_breadth": 3.5
    },
    "dermatological": {
      "n_drugs": 132,
      "n_diseases": 58,
      "mean_breadth": 13.825757575757576,
      "median_breadth": 5.0
    },
    "gastrointestinal": {
      "n_drugs": 119,
      "n_diseases": 81,
      "mean_breadth": 14.487394957983193,
      "median_breadth": 6.0
    },
    "renal": {
      "n_drugs": 117,
      "n_diseases": 43,
      "mean_breadth": 13.965811965811966,
      "median_breadth": 7.0
    }
  },
  "thresholds": {
    "HIGH": {
      "min_drugs": 100,
      "min_breadth": 5
    },
    "MEDIUM": {
      "min_drugs": 50,
      "min_breadth": 4
    },
    "LOW": {
      "default": true
    }
  }
}