{
  "mapped": {
    "DOID:1319": {
      "name": "brain cancer",
      "mondo_id": "MONDO:0001657",
      "mondo_name": "brain cancer",
      "match_type": "name_search_fuzzy"
    },
    "DOID:2394": {
      "name": "ovarian cancer",
      "mondo_id": "MONDO:0008170",
      "mondo_name": "ovarian cancer",
      "match_type": "name_search_fuzzy"
    },
    "DOID:4045": {
      "name": "muscle cancer",
      "mondo_id": "MONDO:0005864",
      "mondo_name": "muscle cancer",
      "match_type": "name_search_fuzzy"
    },
    "DOID:1612": {
      "name": "breast cancer",
      "mondo_id": "MONDO:0007254",
      "mondo_name": "breast cancer",
      "match_type": "name_search_fuzzy"
    },
    "DOID:12306": {
      "name": "vitiligo",
      "mondo_id": "MONDO:0008661",
      "mondo_name": "vitiligo",
      "match_type": "name_search_fuzzy"
    },
    "DOID:3277": {
      "name": "thymus cancer",
      "mondo_id": "MONDO:0002586",
      "mondo_name": "thymus cancer",
      "match_type": "name_search_fuzzy"
    },
    "DOID:585": {
      "name": "nephrolithiasis",
      "mondo_id": "MONDO:0008171",
      "mondo_name": "nephrolithiasis",
      "match_type": "name_search_fuzzy"
    },
    "DOID:11476": {
      "name": "osteoporosis",
      "mondo_id": "MONDO:0019409",
      "mondo_name": "idiopathic juvenile osteoporosis",
      "match_type": "name_search_mondo"
    },
    "DOID:7148": {
      "name": "rheumatoid arthritis",
      "mondo_id": "MONDO:0008383",
      "mondo_name": "rheumatoid arthritis",
      "match_type": "name_search_fuzzy"
    },
    "DOID:13189": {
      "name": "gout",
      "mondo_id": "MONDO:0005393",
      "mondo_name": "gout",
      "match_type": "name_search_fuzzy"
    },
    "DOID:12930": {
      "name": "dilated cardiomyopathy",
      "mondo_id": "MONDO:0005021",
      "mondo_name": "dilated cardiomyopathy",
      "match_type": "name_search_fuzzy"
    },
    "DOID:1312": {
      "name": "focal segmental glomerulosclerosis",
      "mondo_id": "MONDO:0100313",
      "mondo_name": "focal segmental glomerulosclerosis",
      "match_type": "name_search_fuzzy"
    },
    "DOID:5041": {
      "name": "esophageal cancer",
      "mondo_id": "MONDO:0007576",
      "mondo_name": "esophageal cancer",
      "match_type": "name_search_fuzzy"
    },
    "DOID:2043": {
      "name": "hepatitis B",
      "mondo_id": "MONDO:0005344",
      "mondo_name": "hepatitis B virus infection",
      "match_type": "name_search_fuzzy"
    },
    "DOID:12365": {
      "name": "malaria",
      "mondo_id": "MONDO:0005136",
      "mondo_name": "malaria",
      "match_type": "name_search_fuzzy"
    },
    "DOID:1024": {
      "name": "leprosy",
      "mondo_id": "MONDO:0005124",
      "mondo_name": "leprosy",
      "match_type": "name_search_fuzzy"
    },
    "DOID:7147": {
      "name": "ankylosing spondylitis",
      "mondo_id": "MONDO:0005306",
      "mondo_name": "ankylosing spondylitis",
      "match_type": "name_search_fuzzy"
    },
    "DOID:11612": {
      "name": "polycystic ovary syndrome",
      "mondo_id": "MONDO:0008487",
      "mondo_name": "polycystic ovary syndrome",
      "match_type": "name_search_fuzzy"
    },
    "DOID:13378": {
      "name": "Kawasaki disease",
      "mondo_id": "MONDO:0012727",
      "mondo_name": "mucocutaneous lymph node syndrome",
      "match_type": "name_search_fuzzy"
    },
    "DOID:9970": {
      "name": "obesity",
      "mondo_id": "MONDO:0011122",
      "mondo_name": "obesity disorder",
      "match_type": "name_search_mondo"
    },
    "DOID:332": {
      "name": "amyotrophic lateral sclerosis",
      "mondo_id": "MONDO:0004976",
      "mondo_name": "amyotrophic lateral sclerosis",
      "match_type": "name_search_fuzzy"
    },
    "DOID:2841": {
      "name": "asthma",
      "mondo_id": "MONDO:0956975",
      "mondo_name": "T2-high asthma",
      "match_type": "name_search_mondo"
    },
    "DOID:0050742": {
      "name": "nicotine dependence",
      "mondo_id": "MONDO:0008575",
      "mondo_name": "nicotine dependence",
      "match_type": "name_search_fuzzy"
    },
    "DOID:14227": {
      "name": "azoospermia",
      "mondo_id": "MONDO:0100459",
      "mondo_name": "azoospermia",
      "match_type": "name_search_fuzzy"
    },
    "DOID:12236": {
      "name": "primary biliary cholangitis",
      "mondo_id": "MONDO:0005388",
      "mondo_name": "primary biliary cholangitis",
      "match_type": "name_search_fuzzy"
    },
    "DOID:8778": {
      "name": "Crohn's disease",
      "mondo_id": "MONDO:0005011",
      "mondo_name": "Crohn disease",
      "match_type": "name_search_fuzzy"
    },
    "DOID:1459": {
      "name": "hypothyroidism",
      "mondo_id": "MONDO:0005420",
      "mondo_name": "hypothyroidism",
      "match_type": "name_search_fuzzy"
    },
    "DOID:1324": {
      "name": "lung cancer",
      "mondo_id": "MONDO:0008903",
      "mondo_name": "lung cancer",
      "match_type": "name_search_fuzzy"
    },
    "DOID:9744": {
      "name": "type 1 diabetes mellitus",
      "mondo_id": "MONDO:0005147",
      "mondo_name": "type 1 diabetes mellitus",
      "match_type": "name_search_fuzzy"
    },
    "DOID:263": {
      "name": "kidney cancer",
      "mondo_id": "MONDO:0002367",
      "mondo_name": "kidney cancer",
      "match_type": "name_search_fuzzy"
    },
    "DOID:3571": {
      "name": "liver cancer",
      "mondo_id": "MONDO:0002691",
      "mondo_name": "liver cancer",
      "match_type": "name_search_fuzzy"
    },
    "DOID:219": {
      "name": "colon cancer",
      "mondo_id": "MONDO:0002032",
      "mondo_name": "colon carcinoma",
      "match_type": "name_search_fuzzy"
    },
    "DOID:4362": {
      "name": "cervical cancer",
      "mondo_id": "MONDO:0002974",
      "mondo_name": "cervical cancer",
      "match_type": "name_search_fuzzy"
    },
    "DOID:9074": {
      "name": "systemic lupus erythematosus",
      "mondo_id": "MONDO:0007915",
      "mondo_name": "systemic lupus erythematosus",
      "match_type": "name_search_fuzzy"
    },
    "DOID:10283": {
      "name": "prostate cancer",
      "mondo_id": "MONDO:0008315",
      "mondo_name": "prostate cancer",
      "match_type": "name_search_fuzzy"
    },
    "DOID:3083": {
      "name": "chronic obstructive pulmonary disease",
      "mondo_id": "MONDO:0005002",
      "mondo_name": "chronic obstructive pulmonary disease",
      "match_type": "name_search_fuzzy"
    },
    "DOID:11714": {
      "name": "gestational diabetes",
      "mondo_id": "MONDO:0005406",
      "mondo_name": "gestational diabetes",
      "match_type": "name_search_fuzzy"
    },
    "DOID:1909": {
      "name": "melanoma",
      "mondo_id": "MONDO:0005105",
      "mondo_name": "melanoma",
      "match_type": "name_search_fuzzy"
    },
    "DOID:9008": {
      "name": "psoriatic arthritis",
      "mondo_id": "MONDO:0011849",
      "mondo_name": "psoriatic arthritis",
      "match_type": "name_search_fuzzy"
    },
    "DOID:1793": {
      "name": "pancreatic cancer",
      "mondo_id": "MONDO:0005192",
      "mondo_name": "exocrine pancreatic carcinoma",
      "match_type": "name_search_fuzzy"
    },
    "DOID:2377": {
      "name": "multiple sclerosis",
      "mondo_id": "MONDO:0005301",
      "mondo_name": "multiple sclerosis",
      "match_type": "name_search_fuzzy"
    },
    "DOID:1936": {
      "name": "atherosclerosis",
      "mondo_id": "MONDO:0005311",
      "mondo_name": "atherosclerosis",
      "match_type": "name_search_fuzzy"
    },
    "DOID:2531": {
      "name": "hematologic cancer",
      "mondo_id": "MONDO:0044881",
      "mondo_name": "hematopoietic and lymphoid cell neoplasm",
      "match_type": "name_search_fuzzy"
    },
    "DOID:10652": {
      "name": "Alzheimer's disease",
      "mondo_id": "MONDO:0004975",
      "mondo_name": "Alzheimer disease",
      "match_type": "name_search_fuzzy"
    },
    "DOID:1686": {
      "name": "glaucoma",
      "mondo_id": "MONDO:0005041",
      "mondo_name": "glaucoma",
      "match_type": "name_search_fuzzy"
    },
    "DOID:986": {
      "name": "alopecia areata",
      "mondo_id": "MONDO:0005340",
      "mondo_name": "alopecia areata",
      "match_type": "name_search_fuzzy"
    },
    "DOID:4481": {
      "name": "allergic rhinitis",
      "mondo_id": "MONDO:0011786",
      "mondo_name": "allergic rhinitis",
      "match_type": "name_search_fuzzy"
    },
    "DOID:0050741": {
      "name": "alcohol dependence",
      "mondo_id": "MONDO:0007079",
      "mondo_name": "alcohol dependence",
      "match_type": "name_search_fuzzy"
    },
    "DOID:2994": {
      "name": "germ cell cancer",
      "mondo_id": "MONDO:0006290",
      "mondo_name": "malignant germ cell tumor",
      "match_type": "name_search_fuzzy"
    },
    "DOID:8577": {
      "name": "ulcerative colitis",
      "mondo_id": "MONDO:0005101",
      "mondo_name": "ulcerative colitis",
      "match_type": "name_search_fuzzy"
    },
    "DOID:10763": {
      "name": "hypertension",
      "mondo_id": "MONDO:0014135",
      "mondo_name": "pulmonary hypertension, primary, 3",
      "match_type": "name_search_mondo"
    },
    "DOID:8893": {
      "name": "psoriasis",
      "mondo_id": "MONDO:0005083",
      "mondo_name": "psoriasis",
      "match_type": "name_search_fuzzy"
    },
    "DOID:9206": {
      "name": "Barrett's esophagus",
      "mondo_id": "MONDO:0013662",
      "mondo_name": "Barrett esophagus",
      "match_type": "name_search_fuzzy"
    },
    "DOID:1115": {
      "name": "sarcoma",
      "mondo_id": "MONDO:0005089",
      "mondo_name": "sarcoma",
      "match_type": "name_search_fuzzy"
    },
    "DOID:1781": {
      "name": "thyroid cancer",
      "mondo_id": "MONDO:0002108",
      "mondo_name": "thyroid cancer",
      "match_type": "name_search_fuzzy"
    },
    "DOID:0060073": {
      "name": "lymphatic system cancer",
      "mondo_id": "MONDO:0000612",
      "mondo_name": "lymphatic system cancer",
      "match_type": "name_search_fuzzy"
    },
    "DOID:5408": {
      "name": "Paget's disease of bone",
      "mondo_id": "MONDO:0005382",
      "mondo_name": "bone Paget disease",
      "match_type": "name_search_fuzzy"
    },
    "DOID:1192": {
      "name": "peripheral nervous system neoplasm",
      "mondo_id": "MONDO:0001406",
      "mondo_name": "peripheral nervous system neoplasm",
      "match_type": "name_search_fuzzy"
    },
    "DOID:363": {
      "name": "uterine cancer",
      "mondo_id": "MONDO:0002715",
      "mondo_name": "uterine cancer",
      "match_type": "name_search_fuzzy"
    },
    "DOID:3310": {
      "name": "atopic dermatitis",
      "mondo_id": "MONDO:0004980",
      "mondo_name": "atopic eczema",
      "match_type": "name_search_fuzzy"
    },
    "DOID:418": {
      "name": "systemic scleroderma",
      "mondo_id": "MONDO:0005100",
      "mondo_name": "systemic sclerosis",
      "match_type": "name_search_fuzzy"
    },
    "DOID:3070": {
      "name": "high grade glioma",
      "mondo_id": "MONDO:0100342",
      "mondo_name": "malignant glioma",
      "match_type": "name_search_fuzzy"
    },
    "DOID:14221": {
      "name": "abdominal obesity-metabolic syndrome 1",
      "mondo_id": "MONDO:0011565",
      "mondo_name": "metabolic syndrome X",
      "match_type": "name_search_fuzzy"
    },
    "DOID:2174": {
      "name": "ocular cancer",
      "mondo_id": "MONDO:0002236",
      "mondo_name": "ocular cancer",
      "match_type": "name_search_fuzzy"
    },
    "DOID:11934": {
      "name": "head and neck cancer",
      "mondo_id": "MONDO:0005627",
      "mondo_name": "head and neck cancer",
      "match_type": "name_search_fuzzy"
    },
    "DOID:12361": {
      "name": "Graves' disease",
      "mondo_id": "MONDO:0005364",
      "mondo_name": "Graves disease",
      "match_type": "name_search_fuzzy"
    },
    "DOID:11054": {
      "name": "urinary bladder cancer",
      "mondo_id": "MONDO:0001187",
      "mondo_name": "urinary bladder cancer",
      "match_type": "name_search_fuzzy"
    },
    "DOID:3393": {
      "name": "coronary artery disease",
      "mondo_id": "MONDO:0005010",
      "mondo_name": "coronary artery disorder",
      "match_type": "name_search_fuzzy"
    },
    "DOID:4989": {
      "name": "pancreatitis",
      "mondo_id": "MONDO:0008185",
      "mondo_name": "hereditary chronic pancreatitis",
      "match_type": "name_search_mondo"
    },
    "DOID:635": {
      "name": "acquired immunodeficiency syndrome",
      "mondo_id": "MONDO:0012268",
      "mondo_name": "AIDS",
      "match_type": "name_search_fuzzy"
    },
    "DOID:10534": {
      "name": "stomach cancer",
      "mondo_id": "MONDO:0004950",
      "mondo_name": "gastric carcinoma",
      "match_type": "name_search_fuzzy"
    },
    "DOID:4159": {
      "name": "skin cancer",
      "mondo_id": "MONDO:0002898",
      "mondo_name": "skin cancer",
      "match_type": "name_search_fuzzy"
    },
    "DOID:2998": {
      "name": "testicular cancer",
      "mondo_id": "MONDO:0005447",
      "mondo_name": "testicular cancer",
      "match_type": "name_search_fuzzy"
    },
    "DOID:9352": {
      "name": "type 2 diabetes mellitus",
      "mondo_id": "MONDO:0005148",
      "mondo_name": "type 2 diabetes mellitus",
      "match_type": "name_search_fuzzy"
    },
    "DOID:184": {
      "name": "bone cancer",
      "mondo_id": "MONDO:0002129",
      "mondo_name": "bone cancer",
      "match_type": "name_search_fuzzy"
    },
    "DOID:6364": {
      "name": "migraine",
      "mondo_id": "MONDO:0011232",
      "mondo_name": "migraine, familial hemiplegic, 2",
      "match_type": "name_search_mondo"
    },
    "DOID:1826": {
      "name": "epilepsy",
      "mondo_id": "MONDO:0005027",
      "mondo_name": "epilepsy",
      "match_type": "name_search_fuzzy"
    }
  },
  "failed": [],
  "stats": {
    "total": 77,
    "mapped": 77,
    "failed": 0
  }
}